<meta>
	<!-- Auto generated using VSCode MTA:SA Lua by Subtixx -->
	<info author="agatreix" type="script" name="Inventario NoPixel from Class Roleplay" version="0.1.0" />

	<script src="cfg.lua" type="shared" cache='false' />

	<script src="src/client/main.lua" type="client"  cache='false'/>
	<script src="src/server/main.lua" type="server" />
	<script src="src/server/use.lua" type="server" />
	<script src="src/shared/responsive.lua" type="client"  cache='false' />

	<export function='loadItems' type = 'server'/>
	<export function='setItemDescription' type = 'server'/>
	<export function='giveItem' type = 'server'/>
	<export function='takeItem' type = 'server'/>
	<export function='takeAllItems' type = 'server'/>
	<export function='getItem' type = 'server'/>
	<export function='getItem' type = 'client'/>
	<export function='openBau' type = 'server'/>
	<export function='getItemData' type = 'server'/>
	<export function='getItemFromData' type = 'server'/>

	<export function='getPlayerMoney' type="server"/>
	<export function='givePlayerMoney' type="server"/>
	<export function='takePlayerMoney' type="server"/>

	<file src="src/assets/itens/acessorios-1-1.png" />
	<file src="src/assets/itens/acessorios-1-2.png" />
	<file src="src/assets/itens/acessorios-2-1.png" />
	<file src="src/assets/itens/acessorios-2-2.png" />
	<file src="src/assets/itens/acessorios-3-1.png" />
	<file src="src/assets/itens/acessorios-3-2.png" />
	<file src="src/assets/itens/acessorios-4-1.png" />
	<file src="src/assets/itens/acessorios-4-2.png" />
	<file src="src/assets/itens/aderencia.png" />
	<file src="src/assets/itens/adrenalina.png" />
	<file src="src/assets/itens/agua.png" />
	<file src="src/assets/itens/aguasuja.png" />
	<file src="src/assets/itens/ak103.png" />
	<file src="src/assets/itens/algema.png" />
	<file src="src/assets/itens/alianca.png" />
	<file src="src/assets/itens/aluminio.png" />
	<file src="src/assets/itens/ambar.png" />
	<file src="src/assets/itens/ametista.png" />
	<file src="src/assets/itens/analgesico.png" />
	<file src="src/assets/itens/anel.png" />
	<file src="src/assets/itens/anfetamina.png" />
	<file src="src/assets/itens/bacalhau.png" />
	<file src="src/assets/itens/bagre.png" />
	<file src="src/assets/itens/baldeh.png" />
	<file src="src/assets/itens/balinha.png" />
	<file src="src/assets/itens/banana.png" />
	<file src="src/assets/itens/bandagem.png" />
	<file src="src/assets/itens/barraouro.png" />
	<file src="src/assets/itens/baseado.png" />
	<file src="src/assets/itens/bermuda-3-1.png" />
	<file src="src/assets/itens/bermuda-3-10.png" />
	<file src="src/assets/itens/bermuda-3-11.png" />
	<file src="src/assets/itens/bermuda-3-12.png" />
	<file src="src/assets/itens/bermuda-3-13.png" />
	<file src="src/assets/itens/bermuda-3-14.png" />
	<file src="src/assets/itens/bermuda-3-15.png" />
	<file src="src/assets/itens/bermuda-3-16.png" />
	<file src="src/assets/itens/bermuda-3-17.png" />
	<file src="src/assets/itens/bermuda-3-18.png" />
	<file src="src/assets/itens/bermuda-3-19.png" />
	<file src="src/assets/itens/bermuda-3-2.png" />
	<file src="src/assets/itens/bermuda-3-20.png" />
	<file src="src/assets/itens/bermuda-3-21.png" />
	<file src="src/assets/itens/bermuda-3-22.png" />
	<file src="src/assets/itens/bermuda-3-23.png" />
	<file src="src/assets/itens/bermuda-3-24.png" />
	<file src="src/assets/itens/bermuda-3-25.png" />
	<file src="src/assets/itens/bermuda-3-26.png" />
	<file src="src/assets/itens/bermuda-3-27.png" />
	<file src="src/assets/itens/bermuda-3-28.png" />
	<file src="src/assets/itens/bermuda-3-3.png" />
	<file src="src/assets/itens/bermuda-3-4.png" />
	<file src="src/assets/itens/bermuda-3-5.png" />
	<file src="src/assets/itens/bermuda-3-6.png" />
	<file src="src/assets/itens/bermuda-3-7.png" />
	<file src="src/assets/itens/bermuda-3-8.png" />
	<file src="src/assets/itens/bermuda-3-9.png" />
	<file src="src/assets/itens/bermuda-4-1.png" />
	<file src="src/assets/itens/bermuda-4-2.png" />
	<file src="src/assets/itens/bermuda-4-3.png" />
	<file src="src/assets/itens/bermuda-4-4.png" />
	<file src="src/assets/itens/bermuda-6-1.png" />
	<file src="src/assets/itens/bermuda-6-10.png" />
	<file src="src/assets/itens/bermuda-6-11.png" />
	<file src="src/assets/itens/bermuda-6-12.png" />
	<file src="src/assets/itens/bermuda-6-13.png" />
	<file src="src/assets/itens/bermuda-6-14.png" />
	<file src="src/assets/itens/bermuda-6-15.png" />
	<file src="src/assets/itens/bermuda-6-16.png" />
	<file src="src/assets/itens/bermuda-6-17.png" />
	<file src="src/assets/itens/bermuda-6-18.png" />
	<file src="src/assets/itens/bermuda-6-19.png" />
	<file src="src/assets/itens/bermuda-6-2.png" />
	<file src="src/assets/itens/bermuda-6-20.png" />
	<file src="src/assets/itens/bermuda-6-21.png" />
	<file src="src/assets/itens/bermuda-6-22.png" />
	<file src="src/assets/itens/bermuda-6-23.png" />
	<file src="src/assets/itens/bermuda-6-24.png" />
	<file src="src/assets/itens/bermuda-6-25.png" />
	<file src="src/assets/itens/bermuda-6-26.png" />
	<file src="src/assets/itens/bermuda-6-27.png" />
	<file src="src/assets/itens/bermuda-6-28.png" />
	<file src="src/assets/itens/bermuda-6-3.png" />
	<file src="src/assets/itens/bermuda-6-4.png" />
	<file src="src/assets/itens/bermuda-6-5.png" />
	<file src="src/assets/itens/bermuda-6-6.png" />
	<file src="src/assets/itens/bermuda-6-7.png" />
	<file src="src/assets/itens/bermuda-6-8.png" />
	<file src="src/assets/itens/bermuda-6-9.png" />
	<file src="src/assets/itens/blusaf-1-1.png" />
	<file src="src/assets/itens/blusaf-1-2.png" />
	<file src="src/assets/itens/blusaf-1-3.png" />
	<file src="src/assets/itens/blusaf-1-4.png" />
	<file src="src/assets/itens/blusaf-1-5.png" />
	<file src="src/assets/itens/blusaf-1-6.png" />
	<file src="src/assets/itens/blusaf-1-7.png" />
	<file src="src/assets/itens/blusaf-3-1.png" />
	<file src="src/assets/itens/blusaf-3-10.png" />
	<file src="src/assets/itens/blusaf-3-11.png" />
	<file src="src/assets/itens/blusaf-3-12.png" />
	<file src="src/assets/itens/blusaf-3-13.png" />
	<file src="src/assets/itens/blusaf-3-2.png" />
	<file src="src/assets/itens/blusaf-3-3.png" />
	<file src="src/assets/itens/blusaf-3-4.png" />
	<file src="src/assets/itens/blusaf-3-5.png" />
	<file src="src/assets/itens/blusaf-3-6.png" />
	<file src="src/assets/itens/blusaf-3-7.png" />
	<file src="src/assets/itens/blusaf-3-8.png" />
	<file src="src/assets/itens/blusaf-3-9.png" />
	<file src="src/assets/itens/blusaf-4-1.png" />
	<file src="src/assets/itens/blusaf-4-10.png" />
	<file src="src/assets/itens/blusaf-4-11.png" />
	<file src="src/assets/itens/blusaf-4-12.png" />
	<file src="src/assets/itens/blusaf-4-2.png" />
	<file src="src/assets/itens/blusaf-4-3.png" />
	<file src="src/assets/itens/blusaf-4-4.png" />
	<file src="src/assets/itens/blusaf-4-5.png" />
	<file src="src/assets/itens/blusaf-4-6.png" />
	<file src="src/assets/itens/blusaf-4-7.png" />
	<file src="src/assets/itens/blusaf-4-8.png" />
	<file src="src/assets/itens/blusaf-4-9.png" />
	<file src="src/assets/itens/blusaf-5-1.png" />
	<file src="src/assets/itens/blusaf-5-2.png" />
	<file src="src/assets/itens/blusaf-5-3.png" />
	<file src="src/assets/itens/blusaf-5-4.png" />
	<file src="src/assets/itens/blusaf-5-5.png" />
	<file src="src/assets/itens/blusaf-5-6.png" />
	<file src="src/assets/itens/blusaf-5-7.png" />
	<file src="src/assets/itens/blusaf-5-8.png" />
	<file src="src/assets/itens/blusaf-5-9.png" />
	<file src="src/assets/itens/blusaf-6-1.png" />
	<file src="src/assets/itens/blusaf-6-2.png" />
	<file src="src/assets/itens/blusaf-6-3.png" />
	<file src="src/assets/itens/blusaf-6-4.png" />
	<file src="src/assets/itens/blusaf-6-5.png" />
	<file src="src/assets/itens/blusaf-6-6.png" />
	<file src="src/assets/itens/blusaf-6-7.png" />
	<file src="src/assets/itens/blusaf-6-8.png" />
	<file src="src/assets/itens/bolsamedica.png" />
	<file src="src/assets/itens/bone-1-1.png" />
	<file src="src/assets/itens/bone-1-10.png" />
	<file src="src/assets/itens/bone-1-11.png" />
	<file src="src/assets/itens/bone-1-12.png" />
	<file src="src/assets/itens/bone-1-13.png" />
	<file src="src/assets/itens/bone-1-14.png" />
	<file src="src/assets/itens/bone-1-15.png" />
	<file src="src/assets/itens/bone-1-16.png" />
	<file src="src/assets/itens/bone-1-17.png" />
	<file src="src/assets/itens/bone-1-18.png" />
	<file src="src/assets/itens/bone-1-19.png" />
	<file src="src/assets/itens/bone-1-2.png" />
	<file src="src/assets/itens/bone-1-20.png" />
	<file src="src/assets/itens/bone-1-3.png" />
	<file src="src/assets/itens/bone-1-4.png" />
	<file src="src/assets/itens/bone-1-5.png" />
	<file src="src/assets/itens/bone-1-6.png" />
	<file src="src/assets/itens/bone-1-7.png" />
	<file src="src/assets/itens/bone-1-8.png" />
	<file src="src/assets/itens/bone-1-9.png" />
	<file src="src/assets/itens/bone-2-1.png" />
	<file src="src/assets/itens/bone-2-10.png" />
	<file src="src/assets/itens/bone-2-11.png" />
	<file src="src/assets/itens/bone-2-12.png" />
	<file src="src/assets/itens/bone-2-13.png" />
	<file src="src/assets/itens/bone-2-14.png" />
	<file src="src/assets/itens/bone-2-15.png" />
	<file src="src/assets/itens/bone-2-16.png" />
	<file src="src/assets/itens/bone-2-17.png" />
	<file src="src/assets/itens/bone-2-18.png" />
	<file src="src/assets/itens/bone-2-19.png" />
	<file src="src/assets/itens/bone-2-2.png" />
	<file src="src/assets/itens/bone-2-20.png" />
	<file src="src/assets/itens/bone-2-3.png" />
	<file src="src/assets/itens/bone-2-4.png" />
	<file src="src/assets/itens/bone-2-5.png" />
	<file src="src/assets/itens/bone-2-6.png" />
	<file src="src/assets/itens/bone-2-7.png" />
	<file src="src/assets/itens/bone-2-8.png" />
	<file src="src/assets/itens/bone-2-9.png" />
	<file src="src/assets/itens/bota.png" />
	<file src="src/assets/itens/bracelete.png" />
	<file src="src/assets/itens/brincof-1-1.png" />
	<file src="src/assets/itens/brincof-2-1.png" />
	<file src="src/assets/itens/c4.png" />
	<file src="src/assets/itens/cachorroquente.png" />
	<file src="src/assets/itens/cafe.png" />
	<file src="src/assets/itens/caixa.png" />
	<file src="src/assets/itens/caixamisteriosa.png" />
	<file src="src/assets/itens/calca-1-1.png" />
	<file src="src/assets/itens/calca-1-10.png" />
	<file src="src/assets/itens/calca-1-11.png" />
	<file src="src/assets/itens/calca-1-12.png" />
	<file src="src/assets/itens/calca-1-13.png" />
	<file src="src/assets/itens/calca-1-14.png" />
	<file src="src/assets/itens/calca-1-15.png" />
	<file src="src/assets/itens/calca-1-16.png" />
	<file src="src/assets/itens/calca-1-17.png" />
	<file src="src/assets/itens/calca-1-18.png" />
	<file src="src/assets/itens/calca-1-19.png" />
	<file src="src/assets/itens/calca-1-2.png" />
	<file src="src/assets/itens/calca-1-20.png" />
	<file src="src/assets/itens/calca-1-21.png" />
	<file src="src/assets/itens/calca-1-22.png" />
	<file src="src/assets/itens/calca-1-23.png" />
	<file src="src/assets/itens/calca-1-24.png" />
	<file src="src/assets/itens/calca-1-25.png" />
	<file src="src/assets/itens/calca-1-3.png" />
	<file src="src/assets/itens/calca-1-4.png" />
	<file src="src/assets/itens/calca-1-5.png" />
	<file src="src/assets/itens/calca-1-6.png" />
	<file src="src/assets/itens/calca-1-7.png" />
	<file src="src/assets/itens/calca-1-8.png" />
	<file src="src/assets/itens/calca-1-9.png" />
	<file src="src/assets/itens/calca-2-1.png" />
	<file src="src/assets/itens/calca-2-10.png" />
	<file src="src/assets/itens/calca-2-11.png" />
	<file src="src/assets/itens/calca-2-12.png" />
	<file src="src/assets/itens/calca-2-13.png" />
	<file src="src/assets/itens/calca-2-14.png" />
	<file src="src/assets/itens/calca-2-15.png" />
	<file src="src/assets/itens/calca-2-16.png" />
	<file src="src/assets/itens/calca-2-2.png" />
	<file src="src/assets/itens/calca-2-3.png" />
	<file src="src/assets/itens/calca-2-4.png" />
	<file src="src/assets/itens/calca-2-5.png" />
	<file src="src/assets/itens/calca-2-6.png" />
	<file src="src/assets/itens/calca-2-7.png" />
	<file src="src/assets/itens/calca-2-8.png" />
	<file src="src/assets/itens/calca-2-9.png" />
	<file src="src/assets/itens/calca-5-1.png" />
	<file src="src/assets/itens/calca-5-10.png" />
	<file src="src/assets/itens/calca-5-11.png" />
	<file src="src/assets/itens/calca-5-12.png" />
	<file src="src/assets/itens/calca-5-13.png" />
	<file src="src/assets/itens/calca-5-14.png" />
	<file src="src/assets/itens/calca-5-15.png" />
	<file src="src/assets/itens/calca-5-2.png" />
	<file src="src/assets/itens/calca-5-3.png" />
	<file src="src/assets/itens/calca-5-4.png" />
	<file src="src/assets/itens/calca-5-5.png" />
	<file src="src/assets/itens/calca-5-6.png" />
	<file src="src/assets/itens/calca-5-7.png" />
	<file src="src/assets/itens/calca-5-8.png" />
	<file src="src/assets/itens/calca-5-9.png" />
	<file src="src/assets/itens/calca-7-1.png" />
	<file src="src/assets/itens/calca-7-10.png" />
	<file src="src/assets/itens/calca-7-2.png" />
	<file src="src/assets/itens/calca-7-3.png" />
	<file src="src/assets/itens/calca-7-4.png" />
	<file src="src/assets/itens/calca-7-5.png" />
	<file src="src/assets/itens/calca-7-6.png" />
	<file src="src/assets/itens/calca-7-7.png" />
	<file src="src/assets/itens/calca-7-8.png" />
	<file src="src/assets/itens/calca-7-9.png" />
	<file src="src/assets/itens/calcaf-1-1.png" />
	<file src="src/assets/itens/calcaf-1-2.png" />
	<file src="src/assets/itens/calcaf-1-3.png" />
	<file src="src/assets/itens/calcaf-1-4.png" />
	<file src="src/assets/itens/calcaf-1-5.png" />
	<file src="src/assets/itens/calcaf-3-1.png" />
	<file src="src/assets/itens/calcaf-3-10.png" />
	<file src="src/assets/itens/calcaf-3-2.png" />
	<file src="src/assets/itens/calcaf-3-3.png" />
	<file src="src/assets/itens/calcaf-3-4.png" />
	<file src="src/assets/itens/calcaf-3-5.png" />
	<file src="src/assets/itens/calcaf-3-6.png" />
	<file src="src/assets/itens/calcaf-3-7.png" />
	<file src="src/assets/itens/calcaf-3-8.png" />
	<file src="src/assets/itens/calcaf-3-9.png" />
	<file src="src/assets/itens/calcaf-4-1.png" />
	<file src="src/assets/itens/calcaf-4-10.png" />
	<file src="src/assets/itens/calcaf-4-11.png" />
	<file src="src/assets/itens/calcaf-4-12.png" />
	<file src="src/assets/itens/calcaf-4-2.png" />
	<file src="src/assets/itens/calcaf-4-3.png" />
	<file src="src/assets/itens/calcaf-4-4.png" />
	<file src="src/assets/itens/calcaf-4-5.png" />
	<file src="src/assets/itens/calcaf-4-6.png" />
	<file src="src/assets/itens/calcaf-4-7.png" />
	<file src="src/assets/itens/calcaf-4-8.png" />
	<file src="src/assets/itens/calcaf-4-9.png" />
	<file src="src/assets/itens/calcinhaf-1-1.png" />
	<file src="src/assets/itens/calcinhaf-1-2.png" />
	<file src="src/assets/itens/calcinhaf-1-3.png" />
	<file src="src/assets/itens/camarao.png" />
	<file src="src/assets/itens/camera.png" />
	<file src="src/assets/itens/camisa-1-1.png" />
	<file src="src/assets/itens/camisa-1-10.png" />
	<file src="src/assets/itens/camisa-1-11.png" />
	<file src="src/assets/itens/camisa-1-2.png" />
	<file src="src/assets/itens/camisa-1-3.png" />
	<file src="src/assets/itens/camisa-1-4.png" />
	<file src="src/assets/itens/camisa-1-5.png" />
	<file src="src/assets/itens/camisa-1-6.png" />
	<file src="src/assets/itens/camisa-1-7.png" />
	<file src="src/assets/itens/camisa-1-8.png" />
	<file src="src/assets/itens/camisa-1-9.png" />
	<file src="src/assets/itens/camisa-2-1.png" />
	<file src="src/assets/itens/camisa-2-10.png" />
	<file src="src/assets/itens/camisa-2-11.png" />
	<file src="src/assets/itens/camisa-2-12.png" />
	<file src="src/assets/itens/camisa-2-13.png" />
	<file src="src/assets/itens/camisa-2-14.png" />
	<file src="src/assets/itens/camisa-2-15.png" />
	<file src="src/assets/itens/camisa-2-16.png" />
	<file src="src/assets/itens/camisa-2-17.png" />
	<file src="src/assets/itens/camisa-2-18.png" />
	<file src="src/assets/itens/camisa-2-19.png" />
	<file src="src/assets/itens/camisa-2-2.png" />
	<file src="src/assets/itens/camisa-2-20.png" />
	<file src="src/assets/itens/camisa-2-21.png" />
	<file src="src/assets/itens/camisa-2-22.png" />
	<file src="src/assets/itens/camisa-2-23.png" />
	<file src="src/assets/itens/camisa-2-24.png" />
	<file src="src/assets/itens/camisa-2-25.png" />
	<file src="src/assets/itens/camisa-2-26.png" />
	<file src="src/assets/itens/camisa-2-27.png" />
	<file src="src/assets/itens/camisa-2-28.png" />
	<file src="src/assets/itens/camisa-2-29.png" />
	<file src="src/assets/itens/camisa-2-3.png" />
	<file src="src/assets/itens/camisa-2-30.png" />
	<file src="src/assets/itens/camisa-2-31.png" />
	<file src="src/assets/itens/camisa-2-32.png" />
	<file src="src/assets/itens/camisa-2-33.png" />
	<file src="src/assets/itens/camisa-2-34.png" />
	<file src="src/assets/itens/camisa-2-35.png" />
	<file src="src/assets/itens/camisa-2-36.png" />
	<file src="src/assets/itens/camisa-2-37.png" />
	<file src="src/assets/itens/camisa-2-38.png" />
	<file src="src/assets/itens/camisa-2-39.png" />
	<file src="src/assets/itens/camisa-2-4.png" />
	<file src="src/assets/itens/camisa-2-40.png" />
	<file src="src/assets/itens/camisa-2-41.png" />
	<file src="src/assets/itens/camisa-2-42.png" />
	<file src="src/assets/itens/camisa-2-43.png" />
	<file src="src/assets/itens/camisa-2-44.png" />
	<file src="src/assets/itens/camisa-2-45.png" />
	<file src="src/assets/itens/camisa-2-46.png" />
	<file src="src/assets/itens/camisa-2-47.png" />
	<file src="src/assets/itens/camisa-2-48.png" />
	<file src="src/assets/itens/camisa-2-49.png" />
	<file src="src/assets/itens/camisa-2-5.png" />
	<file src="src/assets/itens/camisa-2-50.png" />
	<file src="src/assets/itens/camisa-2-51.png" />
	<file src="src/assets/itens/camisa-2-52.png" />
	<file src="src/assets/itens/camisa-2-53.png" />
	<file src="src/assets/itens/camisa-2-54.png" />
	<file src="src/assets/itens/camisa-2-55.png" />
	<file src="src/assets/itens/camisa-2-56.png" />
	<file src="src/assets/itens/camisa-2-57.png" />
	<file src="src/assets/itens/camisa-2-59.png" />
	<file src="src/assets/itens/camisa-2-6.png" />
	<file src="src/assets/itens/camisa-2-60.png" />
	<file src="src/assets/itens/camisa-2-61.png" />
	<file src="src/assets/itens/camisa-2-62.png" />
	<file src="src/assets/itens/camisa-2-63.png" />
	<file src="src/assets/itens/camisa-2-64.png" />
	<file src="src/assets/itens/camisa-2-65.png" />
	<file src="src/assets/itens/camisa-2-66.png" />
	<file src="src/assets/itens/camisa-2-67.png" />
	<file src="src/assets/itens/camisa-2-68.png" />
	<file src="src/assets/itens/camisa-2-69.png" />
	<file src="src/assets/itens/camisa-2-7.png" />
	<file src="src/assets/itens/camisa-2-70.png" />
	<file src="src/assets/itens/camisa-2-71.png" />
	<file src="src/assets/itens/camisa-2-72.png" />
	<file src="src/assets/itens/camisa-2-73.png" />
	<file src="src/assets/itens/camisa-2-74.png" />
	<file src="src/assets/itens/camisa-2-75.png" />
	<file src="src/assets/itens/camisa-2-76.png" />
	<file src="src/assets/itens/camisa-2-77.png" />
	<file src="src/assets/itens/camisa-2-78.png" />
	<file src="src/assets/itens/camisa-2-79.png" />
	<file src="src/assets/itens/camisa-2-8.png" />
	<file src="src/assets/itens/camisa-2-80.png" />
	<file src="src/assets/itens/camisa-2-81.png" />
	<file src="src/assets/itens/camisa-2-82.png" />
	<file src="src/assets/itens/camisa-2-83.png" />
	<file src="src/assets/itens/camisa-2-84.png" />
	<file src="src/assets/itens/camisa-2-9.png" />
	<file src="src/assets/itens/camisa-3-1.png" />
	<file src="src/assets/itens/camisa-3-2.png" />
	<file src="src/assets/itens/camisa-3-3.png" />
	<file src="src/assets/itens/camisa-3-4.png" />
	<file src="src/assets/itens/camisa-3-5.png" />
	<file src="src/assets/itens/camisa-3-6.png" />
	<file src="src/assets/itens/camisa-3-7.png" />
	<file src="src/assets/itens/camisa-3-8.png" />
	<file src="src/assets/itens/camisa-4-1.png" />
	<file src="src/assets/itens/camisa-4-10.png" />
	<file src="src/assets/itens/camisa-4-11.png" />
	<file src="src/assets/itens/camisa-4-12.png" />
	<file src="src/assets/itens/camisa-4-13.png" />
	<file src="src/assets/itens/camisa-4-14.png" />
	<file src="src/assets/itens/camisa-4-15.png" />
	<file src="src/assets/itens/camisa-4-16.png" />
	<file src="src/assets/itens/camisa-4-17.png" />
	<file src="src/assets/itens/camisa-4-18.png" />
	<file src="src/assets/itens/camisa-4-19.png" />
	<file src="src/assets/itens/camisa-4-2.png" />
	<file src="src/assets/itens/camisa-4-21.png" />
	<file src="src/assets/itens/camisa-4-22.png" />
	<file src="src/assets/itens/camisa-4-3.png" />
	<file src="src/assets/itens/camisa-4-4.png" />
	<file src="src/assets/itens/camisa-4-5.png" />
	<file src="src/assets/itens/camisa-4-6.png" />
	<file src="src/assets/itens/camisa-4-7.png" />
	<file src="src/assets/itens/camisa-4-8.png" />
	<file src="src/assets/itens/camisa-4-9.png" />
	<file src="src/assets/itens/camisa-5-1.png" />
	<file src="src/assets/itens/camisa-5-10.png" />
	<file src="src/assets/itens/camisa-5-11.png" />
	<file src="src/assets/itens/camisa-5-12.png" />
	<file src="src/assets/itens/camisa-5-13.png" />
	<file src="src/assets/itens/camisa-5-14.png" />
	<file src="src/assets/itens/camisa-5-15.png" />
	<file src="src/assets/itens/camisa-5-16.png" />
	<file src="src/assets/itens/camisa-5-17.png" />
	<file src="src/assets/itens/camisa-5-18.png" />
	<file src="src/assets/itens/camisa-5-19.png" />
	<file src="src/assets/itens/camisa-5-2.png" />
	<file src="src/assets/itens/camisa-5-3.png" />
	<file src="src/assets/itens/camisa-5-4.png" />
	<file src="src/assets/itens/camisa-5-5.png" />
	<file src="src/assets/itens/camisa-5-6.png" />
	<file src="src/assets/itens/camisa-5-7.png" />
	<file src="src/assets/itens/camisa-5-8.png" />
	<file src="src/assets/itens/camisa-5-9.png" />
	<file src="src/assets/itens/camisa-6-1.png" />
	<file src="src/assets/itens/camisa-6-10.png" />
	<file src="src/assets/itens/camisa-6-11.png" />
	<file src="src/assets/itens/camisa-6-12.png" />
	<file src="src/assets/itens/camisa-6-13.png" />
	<file src="src/assets/itens/camisa-6-14.png" />
	<file src="src/assets/itens/camisa-6-15.png" />
	<file src="src/assets/itens/camisa-6-2.png" />
	<file src="src/assets/itens/camisa-6-3.png" />
	<file src="src/assets/itens/camisa-6-4.png" />
	<file src="src/assets/itens/camisa-6-5.png" />
	<file src="src/assets/itens/camisa-6-6.png" />
	<file src="src/assets/itens/camisa-6-7.png" />
	<file src="src/assets/itens/camisa-6-8.png" />
	<file src="src/assets/itens/camisa-6-9.png" />
	<file src="src/assets/itens/camisa-7-1.png" />
	<file src="src/assets/itens/camisa-7-10.png" />
	<file src="src/assets/itens/camisa-7-11.png" />
	<file src="src/assets/itens/camisa-7-12.png" />
	<file src="src/assets/itens/camisa-7-13.png" />
	<file src="src/assets/itens/camisa-7-14.png" />
	<file src="src/assets/itens/camisa-7-2.png" />
	<file src="src/assets/itens/camisa-7-3.png" />
	<file src="src/assets/itens/camisa-7-4.png" />
	<file src="src/assets/itens/camisa-7-6.png" />
	<file src="src/assets/itens/camisa-7-7.png" />
	<file src="src/assets/itens/camisa-7-8.png" />
	<file src="src/assets/itens/camisa-7-9.png" />
	<file src="src/assets/itens/camisa-8-1.png" />
	<file src="src/assets/itens/camisa-8-10.png" />
	<file src="src/assets/itens/camisa-8-11.png" />
	<file src="src/assets/itens/camisa-8-12.png" />
	<file src="src/assets/itens/camisa-8-13.png" />
	<file src="src/assets/itens/camisa-8-14.png" />
	<file src="src/assets/itens/camisa-8-15.png" />
	<file src="src/assets/itens/camisa-8-16.png" />
	<file src="src/assets/itens/camisa-8-17.png" />
	<file src="src/assets/itens/camisa-8-2.png" />
	<file src="src/assets/itens/camisa-8-3.png" />
	<file src="src/assets/itens/camisa-8-4.png" />
	<file src="src/assets/itens/camisa-8-5.png" />
	<file src="src/assets/itens/camisa-8-6.png" />
	<file src="src/assets/itens/camisa-8-7.png" />
	<file src="src/assets/itens/camisa-8-8.png" />
	<file src="src/assets/itens/camisa-8-9.png" />
	<file src="src/assets/itens/capsula.png" />
	<file src="src/assets/itens/capuz.png" />
	<file src="src/assets/itens/carnea.png" />
	<file src="src/assets/itens/carneanimala.png" />
	<file src="src/assets/itens/carneanimalb.png" />
	<file src="src/assets/itens/carneanimalc.png" />
	<file src="src/assets/itens/carneanimald.png" />
	<file src="src/assets/itens/carneb.png" />
	<file src="src/assets/itens/carnec.png" />
	<file src="src/assets/itens/carned.png" />
	<file src="src/assets/itens/carpa.png" />
	<file src="src/assets/itens/cassetete.png" />
	<file src="src/assets/itens/cavala.png" />
	<file src="src/assets/itens/cbcebola.png" />
	<file src="src/assets/itens/cbcombo.png" />
	<file src="src/assets/itens/cbfritas.png" />
	<file src="src/assets/itens/cbnuggets.png" />
	<file src="src/assets/itens/cbpacote.png" />
	<file src="src/assets/itens/cbrefri.png" />
	<file src="src/assets/itens/celular.png" />
	<file src="src/assets/itens/laptop.png" />
	<file src="src/assets/itens/tablet.png" />
	<file src="src/assets/itens/vpn.png" />
	<file src="src/assets/itens/chavecarro.png" />
	<file src="src/assets/itens/chavecasa.png" />
	<file src="src/assets/itens/chavemicha.png" />
	<file src="src/assets/itens/chaveportao.png" />
	<file src="src/assets/itens/chaves.png" />
	<file src="src/assets/itens/chip.png" />
	<file src="src/assets/itens/chocolate.png" />
	<file src="src/assets/itens/cigarro.png" />
	<file src="src/assets/itens/caixacigarro.png" />
	<file src="src/assets/itens/circuitos.png" />
	<file src="src/assets/itens/cobre.png" />
	<file src="src/assets/itens/cocaina.png" />
	<file src="src/assets/itens/cola.png" />
	<file src="src/assets/itens/colar.png" />
	<file src="src/assets/itens/contratoa.png" />
	<file src="src/assets/itens/contratob.png" />
	<file src="src/assets/itens/contratoc.png" />
	<file src="src/assets/itens/contratod.png" />
	<file src="src/assets/itens/contratoe.png" />
	<file src="src/assets/itens/contratof.png" />
	<file src="src/assets/itens/contratog.png" />
	<file src="src/assets/itens/contratoh.png" />
	<file src="src/assets/itens/cordas.png" />
	<file src="src/assets/itens/corrente.png" />
	<file src="src/assets/itens/cranio.png" />
	<file src="src/assets/itens/cshotgun.png" />
	<file src="src/assets/itens/dentetubarao.png" />
	<file src="src/assets/itens/desfibrilador.png" />
	<file src="src/assets/itens/diamante.png" />
	<file src="src/assets/itens/dinheiro.png" />
	<file src="src/assets/itens/dinheirosujo.png" />
	<file src="src/assets/itens/doces.png" />
	<file src="src/assets/itens/donut.png" />
	<file src="src/assets/itens/dourado.png" />
	<file src="src/assets/itens/ecstasy.png" />
	<file src="src/assets/itens/elastico.png" />
	<file src="src/assets/itens/energetico.png" />
	<file src="src/assets/itens/esmeralda.png" />
	<file src="src/assets/itens/faca.png" />
	<file src="src/assets/itens/fita.png" />
	<file src="src/assets/itens/fnscar.png" />
	<file src="src/assets/itens/garrafaq.png" />
	<file src="src/assets/itens/garrafavazia.png" />
	<file src="src/assets/itens/gasolina.png" />
	<file src="src/assets/itens/gaze.png" />
	<file src="src/assets/itens/glock.png" />
	<file src="src/assets/itens/hamburguera.png" />
	<file src="src/assets/itens/hamburguerb.png" />
	<file src="src/assets/itens/hamburguerc.png" />
	<file src="src/assets/itens/hbox.png" />
	<file src="src/assets/itens/hkg36.png" />
	<file src="src/assets/itens/hkp7m.png" />
	<file src="src/assets/itens/identidade.png" />
	<file src="src/assets/itens/imbel.png" />
	<file src="src/assets/itens/isca.png" />
	<file src="src/assets/itens/isqueiro.png" />
	<file src="src/assets/itens/jornal.png" />
	<file src="src/assets/itens/katana.png" />
	<file src="src/assets/itens/ketamina.png" />
	<file src="src/assets/itens/kevlar.png" />
	<file src="src/assets/itens/kitifood.png" />
	<file src="src/assets/itens/kitmedico.png" />
	<file src="src/assets/itens/kitreparo.png" />
	<file src="src/assets/itens/laranja.png" />
	<file src="src/assets/itens/lean.png" />
	<file src="src/assets/itens/licensapescador.png" />
	<file src="src/assets/itens/linha.png" />
	<file src="src/assets/itens/linhaa.png" />
	<file src="src/assets/itens/lockpick.png" />
	<file src="src/assets/itens/lockpickq.png" />
	<file src="src/assets/itens/machado.png" />
	<file src="src/assets/itens/machadog.png" />
	<file src="src/assets/itens/maconha.png" />
	<file src="src/assets/itens/madeirarefinada.png" />
	<file src="src/assets/itens/maispropriedades.png" />
	<file src="src/assets/itens/maisveiculos.png" />
	<file src="src/assets/itens/makita.png" />
	<file src="src/assets/itens/martelo.png" />
	<file src="src/assets/itens/mascara-1-1.png" />
	<file src="src/assets/itens/mascara-10-1.png" />
	<file src="src/assets/itens/mascara-11-1.png" />
	<file src="src/assets/itens/mascara-11-2.png" />
	<file src="src/assets/itens/mascara-12-1.png" />
	<file src="src/assets/itens/mascara-12-2.png" />
	<file src="src/assets/itens/mascara-2-1.png" />
	<file src="src/assets/itens/mascara-3-1.png" />
	<file src="src/assets/itens/mascara-4-1.png" />
	<file src="src/assets/itens/mascara-5-1.png" />
	<file src="src/assets/itens/mascara-5-2.png" />
	<file src="src/assets/itens/mascara-6-1.png" />
	<file src="src/assets/itens/mascara-7-1.png" />
	<file src="src/assets/itens/mascara-7-2.png" />
	<file src="src/assets/itens/mascara-8-1.png" />
	<file src="src/assets/itens/mascara-9-1.png" />
	<file src="src/assets/itens/mascarah.png" />
	<file src="src/assets/itens/massapizza.png" />
	<file src="src/assets/itens/massatacos.png" />
	<file src="src/assets/itens/metal.png" />
	<file src="src/assets/itens/metaliquida.png" />
	<file src="src/assets/itens/metanfetamina.png" />
	<file src="src/assets/itens/mfuzil.png" />
	<file src="src/assets/itens/microsmg.png" />
	<file src="src/assets/itens/minismg.png" />
	<file src="src/assets/itens/miraa.png" />
	<file src="src/assets/itens/mirab.png" />
	<file src="src/assets/itens/mochila.png" />
	<file src="src/assets/itens/moedaa.png" />
	<file src="src/assets/itens/moedab.png" />
	<file src="src/assets/itens/moedac.png" />
	<file src="src/assets/itens/molhopizza.png" />
	<file src="src/assets/itens/motora.png" />
	<file src="src/assets/itens/motorb.png" />
	<file src="src/assets/itens/motorc.png" />
	<file src="src/assets/itens/mouse.png" />
	<file src="src/assets/itens/mp5.png" />
	<file src="src/assets/itens/mpistola.png" />
	<file src="src/assets/itens/mrifle.png" />
	<file src="src/assets/itens/mshotgun.png" />
	<file src="src/assets/itens/msmg.png" />
	<file src="src/assets/itens/oculos-1-1.png" />
	<file src="src/assets/itens/oculos-1-10.png" />
	<file src="src/assets/itens/oculos-1-11.png" />
	<file src="src/assets/itens/oculos-1-12.png" />
	<file src="src/assets/itens/oculos-1-13.png" />
	<file src="src/assets/itens/oculos-1-14.png" />
	<file src="src/assets/itens/oculos-1-15.png" />
	<file src="src/assets/itens/oculos-1-2.png" />
	<file src="src/assets/itens/oculos-1-3.png" />
	<file src="src/assets/itens/oculos-1-4.png" />
	<file src="src/assets/itens/oculos-1-5.png" />
	<file src="src/assets/itens/oculos-1-6.png" />
	<file src="src/assets/itens/oculos-1-7.png" />
	<file src="src/assets/itens/oculos-1-8.png" />
	<file src="src/assets/itens/oculos-1-9.png" />
	<file src="src/assets/itens/oculos-2-1.png" />
	<file src="src/assets/itens/oculos-2-2.png" />
	<file src="src/assets/itens/oculos-2-3.png" />
	<file src="src/assets/itens/oculos-2-4.png" />
	<file src="src/assets/itens/oculos-2-5.png" />
	<file src="src/assets/itens/oculos-2-6.png" />
	<file src="src/assets/itens/oculos-2-7.png" />
	<file src="src/assets/itens/oculos-2-8.png" />
	<file src="src/assets/itens/oleo.png" />
	<file src="src/assets/itens/ouro.png" />
	<file src="src/assets/itens/pacotea.png" />
	<file src="src/assets/itens/pacoteb.png" />
	<file src="src/assets/itens/pacotec.png" />
	<file src="src/assets/itens/pacotecebolas.png" />
	<file src="src/assets/itens/pacoted.png" />
	<file src="src/assets/itens/pacotee.png" />
	<file src="src/assets/itens/pacotef.png" />
	<file src="src/assets/itens/pacotefritas.png" />
	<file src="src/assets/itens/pacoteg.png" />
	<file src="src/assets/itens/pacoteh.png" />
	<file src="src/assets/itens/pacotei.png" />
	<file src="src/assets/itens/pacotej.png" />
	<file src="src/assets/itens/pacotenuggets.png" />
	<file src="src/assets/itens/pacu.png" />
	<file src="src/assets/itens/pano.png" />
	<file src="src/assets/itens/panoa.png" />
	<file src="src/assets/itens/pao.png" />
	<file src="src/assets/itens/paraquedas.png" />
	<file src="src/assets/itens/parteeletricaa.png" />
	<file src="src/assets/itens/parteeletricab.png" />
	<file src="src/assets/itens/parteeletricac.png" />
	<file src="src/assets/itens/parteeletricad.png" />
	<file src="src/assets/itens/partfuzila1.png" />
	<file src="src/assets/itens/partfuzila2.png" />
	<file src="src/assets/itens/partfuzila3.png" />
	<file src="src/assets/itens/partfuzilb1.png" />
	<file src="src/assets/itens/partfuzilb2.png" />
	<file src="src/assets/itens/partfuzilb3.png" />
	<file src="src/assets/itens/partpistolaa1.png" />
	<file src="src/assets/itens/partpistolaa2.png" />
	<file src="src/assets/itens/partpistolab1.png" />
	<file src="src/assets/itens/partpistolab2.png" />
	<file src="src/assets/itens/partshotguna1.png" />
	<file src="src/assets/itens/partshotguna2.png" />
	<file src="src/assets/itens/partshotguna3.png" />
	<file src="src/assets/itens/partsmga1.png" />
	<file src="src/assets/itens/partsmga2.png" />
	<file src="src/assets/itens/partsmgb1.png" />
	<file src="src/assets/itens/partsmgb2.png" />
	<file src="src/assets/itens/pastabase.png" />
	<file src="src/assets/itens/pedra.png" />
	<file src="src/assets/itens/peleanimal.png" />
	<file src="src/assets/itens/pendrive.png" />
	<file src="src/assets/itens/picareta.png" />
	<file src="src/assets/itens/pilhas.png" />
	<file src="src/assets/itens/pirarucu.png" />
	<file src="src/assets/itens/pizza.png" />
	<file src="src/assets/itens/placa.png" />
	<file src="src/assets/itens/pneua.png" />
	<file src="src/assets/itens/pneub.png" />
	<file src="src/assets/itens/pneuc.png" />
	<file src="src/assets/itens/pneus.png" />
	<file src="src/assets/itens/polvo.png" />
	<file src="src/assets/itens/polvoraa.png" />
	<file src="src/assets/itens/polvorab.png" />
	<file src="src/assets/itens/polvorac.png" />
	<file src="src/assets/itens/polvorad.png" />
	<file src="src/assets/itens/portaa.png" />
	<file src="src/assets/itens/portab.png" />
	<file src="src/assets/itens/portac.png" />
	<file src="src/assets/itens/queijo.png" />
	<file src="src/assets/itens/radio.png" />
	<file src="src/assets/itens/radioscanner.png" />
	<file src="src/assets/itens/rasteiraf-6-1.png" />
	<file src="src/assets/itens/rasteiraf-6-10.png" />
	<file src="src/assets/itens/rasteiraf-6-2.png" />
	<file src="src/assets/itens/rasteiraf-6-3.png" />
	<file src="src/assets/itens/rasteiraf-6-4.png" />
	<file src="src/assets/itens/rasteiraf-6-5.png" />
	<file src="src/assets/itens/rasteiraf-6-6.png" />
	<file src="src/assets/itens/rasteiraf-6-7.png" />
	<file src="src/assets/itens/rasteiraf-6-8.png" />
	<file src="src/assets/itens/rasteiraf-6-9.png" />
	<file src="src/assets/itens/refeicaoa.png" />
	<file src="src/assets/itens/refeicaob.png" />
	<file src="src/assets/itens/relogio-1-1.png" />
	<file src="src/assets/itens/relogio-1-2.png" />
	<file src="src/assets/itens/relogio-2-1.png" />
	<file src="src/assets/itens/relogio-2-2.png" />
	<file src="src/assets/itens/relogio-2-3.png" />
	<file src="src/assets/itens/relogio-2-4.png" />
	<file src="src/assets/itens/revolver.png" />
	<file src="src/assets/itens/roupamergulho.png" />
	<file src="src/assets/itens/rubi.png" />
	<file src="src/assets/itens/safira.png" />
	<file src="src/assets/itens/salada.png" />
	<file src="src/assets/itens/saltof-3-1.png" />
	<file src="src/assets/itens/saltof-3-10.png" />
	<file src="src/assets/itens/saltof-3-2.png" />
	<file src="src/assets/itens/saltof-3-3.png" />
	<file src="src/assets/itens/saltof-3-4.png" />
	<file src="src/assets/itens/saltof-3-5.png" />
	<file src="src/assets/itens/saltof-3-6.png" />
	<file src="src/assets/itens/saltof-3-7.png" />
	<file src="src/assets/itens/saltof-3-8.png" />
	<file src="src/assets/itens/saltof-3-9.png" />
	<file src="src/assets/itens/sandalia-1-1.png" />
	<file src="src/assets/itens/sandalia-1-10.png" />
	<file src="src/assets/itens/sandalia-1-11.png" />
	<file src="src/assets/itens/sandalia-1-12.png" />
	<file src="src/assets/itens/sandalia-1-13.png" />
	<file src="src/assets/itens/sandalia-1-14.png" />
	<file src="src/assets/itens/sandalia-1-15.png" />
	<file src="src/assets/itens/sandalia-1-16.png" />
	<file src="src/assets/itens/sandalia-1-17.png" />
	<file src="src/assets/itens/sandalia-1-18.png" />
	<file src="src/assets/itens/sandalia-1-19.png" />
	<file src="src/assets/itens/sandalia-1-2.png" />
	<file src="src/assets/itens/sandalia-1-3.png" />
	<file src="src/assets/itens/sandalia-1-4.png" />
	<file src="src/assets/itens/sandalia-1-5.png" />
	<file src="src/assets/itens/sandalia-1-6.png" />
	<file src="src/assets/itens/sandalia-1-7.png" />
	<file src="src/assets/itens/sandalia-1-8.png" />
	<file src="src/assets/itens/sandalia-1-9.png" />
	<file src="src/assets/itens/sandalia-5-1.png" />
	<file src="src/assets/itens/sandalia-5-10.png" />
	<file src="src/assets/itens/sandalia-5-11.png" />
	<file src="src/assets/itens/sandalia-5-12.png" />
	<file src="src/assets/itens/sandalia-5-13.png" />
	<file src="src/assets/itens/sandalia-5-14.png" />
	<file src="src/assets/itens/sandalia-5-15.png" />
	<file src="src/assets/itens/sandalia-5-16.png" />
	<file src="src/assets/itens/sandalia-5-17.png" />
	<file src="src/assets/itens/sandalia-5-18.png" />
	<file src="src/assets/itens/sandalia-5-19.png" />
	<file src="src/assets/itens/sandalia-5-2.png" />
	<file src="src/assets/itens/sandalia-5-3.png" />
	<file src="src/assets/itens/sandalia-5-4.png" />
	<file src="src/assets/itens/sandalia-5-5.png" />
	<file src="src/assets/itens/sandalia-5-6.png" />
	<file src="src/assets/itens/sandalia-5-7.png" />
	<file src="src/assets/itens/sandalia-5-8.png" />
	<file src="src/assets/itens/sandalia-5-9.png" />
	<file src="src/assets/itens/sanduiche.png" />
	<file src="src/assets/itens/sapatilhaf-5-1.png" />
	<file src="src/assets/itens/sapatilhaf-5-10.png" />
	<file src="src/assets/itens/sapatilhaf-5-2.png" />
	<file src="src/assets/itens/sapatilhaf-5-3.png" />
	<file src="src/assets/itens/sapatilhaf-5-4.png" />
	<file src="src/assets/itens/sapatilhaf-5-5.png" />
	<file src="src/assets/itens/sapatilhaf-5-6.png" />
	<file src="src/assets/itens/sapatilhaf-5-7.png" />
	<file src="src/assets/itens/sapatilhaf-5-8.png" />
	<file src="src/assets/itens/sapatilhaf-5-9.png" />
	<file src="src/assets/itens/seda.png" />
	<file src="src/assets/itens/semblantea.png" />
	<file src="src/assets/itens/semblanteb.png" />
	<file src="src/assets/itens/sementemaconha.png" />
	<file src="src/assets/itens/shortf-2-1.png" />
	<file src="src/assets/itens/shortf-2-10.png" />
	<file src="src/assets/itens/shortf-2-11.png" />
	<file src="src/assets/itens/shortf-2-12.png" />
	<file src="src/assets/itens/shortf-2-13.png" />
	<file src="src/assets/itens/shortf-2-14.png" />
	<file src="src/assets/itens/shortf-2-15.png" />
	<file src="src/assets/itens/shortf-2-16.png" />
	<file src="src/assets/itens/shortf-2-17.png" />
	<file src="src/assets/itens/shortf-2-18.png" />
	<file src="src/assets/itens/shortf-2-19.png" />
	<file src="src/assets/itens/shortf-2-2.png" />
	<file src="src/assets/itens/shortf-2-3.png" />
	<file src="src/assets/itens/shortf-2-4.png" />
	<file src="src/assets/itens/shortf-2-5.png" />
	<file src="src/assets/itens/shortf-2-6.png" />
	<file src="src/assets/itens/shortf-2-7.png" />
	<file src="src/assets/itens/shortf-2-8.png" />
	<file src="src/assets/itens/shortf-2-9.png" />
	<file src="src/assets/itens/shotgun.png" />
	<file src="src/assets/itens/silenciadora.png" />
	<file src="src/assets/itens/silenciadorb.png" />
	<file src="src/assets/itens/silenciadorc.png" />
	<file src="src/assets/itens/sinkalmy.png" />
	<file src="src/assets/itens/slots.png" />
	<file src="src/assets/itens/smt40.png" />
	<file src="src/assets/itens/soqueira.png" />
	<file src="src/assets/itens/sprite.png" />
	<file src="src/assets/itens/sprunk.png" />
	<file src="src/assets/itens/sucobanana.png" />
	<file src="src/assets/itens/sucolaranja.png" />
	<file src="src/assets/itens/sucotangerina.png" />
	<file src="src/assets/itens/sucouva.png" />
	<file src="src/assets/itens/sutiaf-1-1.png" />
	<file src="src/assets/itens/sutiaf-1-2.png" />
	<file src="src/assets/itens/sutiaf-1-3.png" />
	<file src="src/assets/itens/tabletpolicial.png" />
	<file src="src/assets/itens/tacos.png" />
	<file src="src/assets/itens/tacospeixe.png" />
	<file src="src/assets/itens/tambaqui.png" />
	<file src="src/assets/itens/tangerina.png" />
	<file src="src/assets/itens/taser.png" />
	<file src="src/assets/itens/taurus.png" />
	<file src="src/assets/itens/tec9.png" />
	<file src="src/assets/itens/tecido.png" />
	<file src="src/assets/itens/teclado.png" />
	<file src="src/assets/itens/tenis-2-1.png" />
	<file src="src/assets/itens/tenis-2-10.png" />
	<file src="src/assets/itens/tenis-2-11.png" />
	<file src="src/assets/itens/tenis-2-12.png" />
	<file src="src/assets/itens/tenis-2-13.png" />
	<file src="src/assets/itens/tenis-2-14.png" />
	<file src="src/assets/itens/tenis-2-15.png" />
	<file src="src/assets/itens/tenis-2-16.png" />
	<file src="src/assets/itens/tenis-2-17.png" />
	<file src="src/assets/itens/tenis-2-2.png" />
	<file src="src/assets/itens/tenis-2-3.png" />
	<file src="src/assets/itens/tenis-2-4.png" />
	<file src="src/assets/itens/tenis-2-5.png" />
	<file src="src/assets/itens/tenis-2-6.png" />
	<file src="src/assets/itens/tenis-2-7.png" />
	<file src="src/assets/itens/tenis-2-8.png" />
	<file src="src/assets/itens/tenis-2-9.png" />
	<file src="src/assets/itens/tenis-3-1.png" />
	<file src="src/assets/itens/tenis-3-2.png" />
	<file src="src/assets/itens/tenis-3-3.png" />
	<file src="src/assets/itens/tenis-3-4.png" />
	<file src="src/assets/itens/tenis-3-5.png" />
	<file src="src/assets/itens/tenis-3-6.png" />
	<file src="src/assets/itens/tenis-4-1.png" />
	<file src="src/assets/itens/tenis-4-2.png" />
	<file src="src/assets/itens/tenis-4-3.png" />
	<file src="src/assets/itens/tenis-6-1.png" />
	<file src="src/assets/itens/tenis-6-2.png" />
	<file src="src/assets/itens/tenis-6-3.png" />
	<file src="src/assets/itens/tenis-6-4.png" />
	<file src="src/assets/itens/tenis-6-5.png" />
	<file src="src/assets/itens/tenis-6-6.png" />
	<file src="src/assets/itens/tenis-7-1.png" />
	<file src="src/assets/itens/tenis-7-2.png" />
	<file src="src/assets/itens/tenis-7-3.png" />
	<file src="src/assets/itens/tenis-7-4.png" />
	<file src="src/assets/itens/tenis-7-5.png" />
	<file src="src/assets/itens/tenis-8-1.png" />
	<file src="src/assets/itens/tenis-8-2.png" />
	<file src="src/assets/itens/tenis-8-3.png" />
	<file src="src/assets/itens/tenis-8-4.png" />
	<file src="src/assets/itens/tenisf-4-1.png" />
	<file src="src/assets/itens/tenisf-4-10.png" />
	<file src="src/assets/itens/tenisf-4-2.png" />
	<file src="src/assets/itens/tenisf-4-3.png" />
	<file src="src/assets/itens/tenisf-4-4.png" />
	<file src="src/assets/itens/tenisf-4-5.png" />
	<file src="src/assets/itens/tenisf-4-6.png" />
	<file src="src/assets/itens/tenisf-4-7.png" />
	<file src="src/assets/itens/tenisf-4-8.png" />
	<file src="src/assets/itens/tenisf-4-9.png" />
	<file src="src/assets/itens/tilapia.png" />
	<file src="src/assets/itens/titanium.png" />
	<file src="src/assets/itens/tora.png" />
	<file src="src/assets/itens/trocarnome.png" />
	<file src="src/assets/itens/turbina.png" />
	<file src="src/assets/itens/turquesa.png" />
	<file src="src/assets/itens/twcombo.png" />
	<file src="src/assets/itens/twfritas.png" />
	<file src="src/assets/itens/twrefri.png" />
	<file src="src/assets/itens/uva.png" />
	<file src="src/assets/itens/vaper.png" />
	<file src="src/assets/itens/vara.png" />
	<file src="src/assets/itens/vaso.png" />
	<file src="src/assets/itens/vest.png" />
	<file src="src/assets/itens/vestidof-2-1.png" />
	<file src="src/assets/itens/vestidof-2-10.png" />
	<file src="src/assets/itens/vestidof-2-2.png" />
	<file src="src/assets/itens/vestidof-2-3.png" />
	<file src="src/assets/itens/vestidof-2-4.png" />
	<file src="src/assets/itens/vestidof-2-5.png" />
	<file src="src/assets/itens/vestidof-2-6.png" />
	<file src="src/assets/itens/vestidof-2-7.png" />
	<file src="src/assets/itens/vestidof-2-8.png" />
	<file src="src/assets/itens/vestidof-2-9.png" />
	<file src="src/assets/itens/winchester.png" />
	<file src="src/assets/itens/xaropecodeina.png" />
	<file src="src/assets/itens/xbox.png" />
	<file src="src/assets/itens/ziplock.png" />
	<file src="src/assets/itens/distintivo.png" />
	<file src="src/assets/itens/frangofrito.png" />
	<file src="src/assets/itens/frango.png" />
	<file src="src/assets/itens/cbburguer.png" />
	<file src="src/assets/itens/frangoempanado.png" />
	<file src="src/assets/itens/alface.png" />


	<file src="src/assets/itens/baggie.png" />
	<file src="src/assets/itens/budmolhado.png" />
	<file src="src/assets/itens/budseco.png" />
	<file src="src/assets/itens/fertilizante.png" />
	<file src="src/assets/itens/regador.png" />
	<file src="src/assets/itens/sementeF.png" />
	<file src="src/assets/itens/sementeM.png" />
	<file src="src/assets/itens/weedbox.png" />

	<file src='src/assets/fonts/Poppins-Regular.ttf'/>
	<file src='src/assets/fonts/Poppins-Medium.ttf'/>
	<file src='src/assets/fonts/Poppins-SemiBold.ttf'/>
	<file src='src/assets/fonts/Poppins-Bold.ttf'/>
	<file src='src/assets/fonts/Roboto-Regular.ttf'/>
	<file src='src/assets/fonts/Roboto-Medium.ttf'/>
	<file src='src/assets/fonts/Roboto-Bold.ttf'/>

	<export function='giveItem' type='server'/>
	<export function='takeItem' type='server'/>

</meta>